{
    "title": "# Tonami",
    "instructions": "Please wait for instructions from the interviewer.  \n   \n Please note that your audio will be recorded.  \n By clicking Next, you agree to allowing your recordings to be shared anonymously with the team and trusted evaluators.",
    "calibration": "According to all known laws of aviation, there is no way a bee should be able to fly. Do you think bees care what humans think is impossible?",
    "calibration_end": "Thank you for patience. You may now proceed to the next module",
    "exercises": [
        {
            "character": "罚",
            "pinyin": "fá",
            "tone": 2,
            "translation": "punish",
            "fileName": "fa2_FV1_MP3"
        },
        {
            "character": "法",
            "pinyin": "fǎ",
            "tone": 3,
            "translation": "law",
            "fileName": "fa3_MV1_MP3"
        },
        {
            "character": "发",
            "pinyin": "fā",
            "tone": 1,
            "translation": "send",
            "fileName": "fa1_FV3_MP3"
        },
        {
            "character": "髪",
            "pinyin": "fà",
            "tone": 4,
            "translation": "hairstyle",
            "fileName": "fa4_MV2_MP3"
        },
        {
            "character": "明",
            "pinyin": "míng",
            "tone": 2,
            "translation": "bright",
            "fileName": "ming2_FV2_MP3"
        },
        {
            "character": "玩",
            "pinyin": "wán",
            "tone": 2,
            "translation": "play",
            "fileName": "wan2_MV3_MP3"
        },
        {
            "character": "我",
            "pinyin": "wǒ",
            "tone": 3,
            "translation": "I",
            "fileName": "wo3_MV1_MP3"
        },
        {
            "character": "八",
            "pinyin": "bā",
            "tone": 1,
            "translation": "eight",
            "fileName": "ba1_MV3_MP3"
        },
        {
            "character": "干",
            "pinyin": "gàn",
            "tone": 4,
            "translation": "dry",
            "fileName": "gan4_FV1_MP3"
        },
        {
            "character": "五",
            "pinyin": "wǔ",
            "tone": 3,
            "translation": "five",
            "fileName": "wu3_MV3_MP3"
        },
        {
            "character": "里",
            "pinyin": "lǐ",
            "tone": 3,
            "translation": "inside",
            "fileName": "li3_FV2_MP3"
        },
        {
            "character": "压",
            "pinyin": "yā",
            "tone": 1,
            "translation": "pressure",
            "fileName": "ya1_MV2_MP3"
        },
        {
            "character": "拉",
            "pinyin": "lā",
            "tone": 1,
            "translation": "pull",
            "fileName": "la1_FV3_MP3"
        },
        {
            "character": "福",
            "pinyin": "fú",
            "tone": 2,
            "translation": "blessing",
            "fileName": "fu2_FV2_MP3"
        },
        {
            "character": "肉",
            "pinyin": "ròu",
            "tone": 4,
            "translation": "meat",
            "fileName": "rou4_MV3_MP3"
        },
        {
            "character": "冰",
            "pinyin": "bīng",
            "tone": 1,
            "translation": "ice",
            "fileName": "bing1_MV1_MP3"
        },
        {
            "character": "您",
            "pinyin": "ní",
            "tone": 2,
            "translation": "you (polite)",
            "fileName": "ni2_MV1_MP3"
        },
        {
            "character": "兔",
            "pinyin": "tù",
            "tone": 4,
            "translation": "rabbit",
            "fileName": "tu4_FV2_MP3"
        },
        {
            "character": "样",
            "pinyin": "yàng",
            "tone": 4,
            "translation": "sample",
            "fileName": "yang4_MV1_MP3"
        },
        {
            "character": "宝",
            "pinyin": "bǎo",
            "tone": 3,
            "translation": "previous",
            "fileName": "bao3_FV3_MP3"
        },
        {
            "character": "罚",
            "pinyin": "fá",
            "tone": 2,
            "translation": "punish",
            "fileName": "fa2_FV1_MP3"
        },
        {
            "character": "法",
            "pinyin": "fǎ",
            "tone": 3,
            "translation": "law",
            "fileName": "fa3_MV1_MP3"
        },
        {
            "character": "发",
            "pinyin": "fā",
            "tone": 1,
            "translation": "send",
            "fileName": "fa1_FV3_MP3"
        },
        {
            "character": "髪",
            "pinyin": "fà",
            "tone": 4,
            "translation": "hairstyle",
            "fileName": "fa4_MV2_MP3"
        }
    ],
    "ratings": [
        {
            "upperlimit": 0.5,
            "label": "Great job!  \n Practice some more to make sure you've got it, or move onto the next module."
        },
        {
            "upperlimit": 0.0,
            "label": "Almost there!  \n It sounds good, but there are still some parts that could be improved if you wanted to."
        },
        {
            "upperlimit": 0.0,
            "label": "Not quite, try again?  \n Listen to your recording versus the example's and try to hear the differences."
        }
    ],
    "end_page": "Thank you for your participation❤️  \n If you would like to know more, please contact us at fydp.team3@gmail.com"
}